{
  "en": {
    "cultures_data": "Cultures Data",
    "search_placeholder": "Search...",
    "all_regions": "All Regions",
    "western": "Western",
    "chinese": "Chinese",
    "arab": "Arab",
    "all_topics": "All Topics",
    "food": "Food",
    "education": "Education",
    "work_life": "Work Life",
    "sport": "Sport",
    "holiday": "Holiday",
    "family": "Family",
    "greeting": "Greeting",
    "show": "Show",
    "entries": "Entries",
    "index": "Index",
    "region": "Region",
    "attribute": "Attribute",
    "values": "Values",
    "topic": "Topic",
    "reason": "Reason",
    "add": "Add",
    "notify": "Notify",
    "variation": "Variation"
  },
  "ch": {
    "cultures_data": "文化数据",
    "search_placeholder": "搜索...",
    "all_regions": "所有地区",
    "western": "西方",
    "chinese": "中国",
    "arab": "阿拉伯",
    "all_topics": "所有话题",
    "food": "食物",
    "education": "教育",
    "work_life": "工作生活",
    "sport": "运动",
    "holiday": "假期",
    "family": "家庭",
    "greeting": "问候",
    "show": "展示",
    "entries": "条目",
    "index": "索引",
    "region": "地区",
    "attribute": "属性",
    "values": "值",
    "topic": "话题",
    "reason": "原因",
    "add": "添加",
    "notify": "通知",
    "variation": "变异"
  },
  "ar": {
    "cultures_data": "بيانات الثقافات",
    "search_placeholder": "بحث...",
    "all_regions": "جميع المناطق",
    "western": "الغربي",
    "chinese": "الصيني",
    "arab": "العربي",
    "all_topics": "جميع المواضيع",
    "food": "طعام",
    "education": "تعليم",
    "work_life": "حياة العمل",
    "sport": "رياضة",
    "holiday": "عطلة",
    "family": "عائلة",
    "greeting": "تحية",
    "show": "عرض",
    "entries": "مدخلات",
    "index": "فهرس",
    "region": "منطقة",
    "attribute": "خاصية",
    "values": "قيم",
    "topic": "موضوع",
    "reason": "سبب",
    "add": "إضافة",
    "notify": "إعلام",
    "variation": "إختلاف"
  }
}
